litestar_flags/__init__.py
litestar_flags/admin/__init__.py
litestar_flags/admin/audit.py
litestar_flags/admin/controllers/__init__.py
litestar_flags/admin/controllers/analytics.py
litestar_flags/admin/controllers/environments.py
litestar_flags/admin/controllers/flags.py
litestar_flags/admin/controllers/overrides.py
litestar_flags/admin/controllers/rules.py
litestar_flags/admin/controllers/segments.py
litestar_flags/admin/dto.py
litestar_flags/admin/guards.py
litestar_flags/admin/plugin.py
litestar_flags/analytics/__init__.py
litestar_flags/analytics/aggregator.py
litestar_flags/analytics/base.py
litestar_flags/analytics/collectors/__init__.py
litestar_flags/analytics/collectors/database.py
litestar_flags/analytics/collectors/memory.py
litestar_flags/analytics/exporters/__init__.py
litestar_flags/analytics/exporters/otel.py
litestar_flags/analytics/exporters/prometheus.py
litestar_flags/analytics/models.py
litestar_flags/analytics/protocols.py
litestar_flags/bootstrap.py
litestar_flags/cache.py
litestar_flags/client.py
litestar_flags/config.py
litestar_flags/context.py
litestar_flags/contrib/__init__.py
litestar_flags/contrib/cache_invalidation.py
litestar_flags/contrib/logging.py
litestar_flags/contrib/openfeature.py
litestar_flags/contrib/otel.py
litestar_flags/contrib/workflows/__init__.py
litestar_flags/contrib/workflows/steps.py
litestar_flags/contrib/workflows/types.py
litestar_flags/contrib/workflows/workflows.py
litestar_flags/decorators.py
litestar_flags/engine.py
litestar_flags/environment.py
litestar_flags/environment_middleware.py
litestar_flags/environment_resolver.py
litestar_flags/exceptions.py
litestar_flags/health.py
litestar_flags/middleware.py
litestar_flags/models/__init__.py
litestar_flags/models/base.py
litestar_flags/models/environment.py
litestar_flags/models/environment_flag.py
litestar_flags/models/flag.py
litestar_flags/models/override.py
litestar_flags/models/rule.py
litestar_flags/models/schedule.py
litestar_flags/models/segment.py
litestar_flags-0.2.1.dist-info/WHEEL
litestar_flags-0.2.1.dist-info/entry_points.txt
litestar_flags-0.2.1.dist-info/METADATA
litestar_flags-0.2.1.dist-info/RECORD
